configuration_loader/__init__.py
configuration_loader/loaders/__init__.py
configuration_loader/loaders/base.py
configuration_loader/loaders/base_loader.py
configuration_loader/loaders/basic_loader.py
configuration_loader/loaders/environment.py
configuration_loader/loaders/json.py
configuration_loader/mergers/__init__.py
configuration_loader/mergers/base.py
configuration_loader/mergers/default.py
configuration_loader/parsers/__init__.py
configuration_loader/parsers/base.py
configuration_loader/parsers/default.py
examples/__init__.py
examples/example.py
tests/__init__.py
tests/example.py
settings_loader-0.1.4.dist-info/LICENSE
settings_loader-0.1.4.dist-info/METADATA
settings_loader-0.1.4.dist-info/WHEEL
settings_loader-0.1.4.dist-info/top_level.txt
settings_loader-0.1.4.dist-info/RECORD
