Metadata-Version: 2.1
Name: settings-loader
Version: 0.1.4
Summary: A small configuration_loader loader package
Home-page: https://github.com/Tiendeo/settings_loader
Author: Tiendeo
Author-email: info.it@gmail.com
License: UNKNOWN
Platform: UNKNOWN
Classifier: Programming Language :: Python :: 3
Classifier: License :: OSI Approved :: MIT License
Classifier: Operating System :: OS Independent
Requires-Dist: inflection (==0.3.1)
